soundmaker/__init__.py
soundmaker/main.py
soundmaker/utils.py
soundmaker-1.0.0.dist-info/LICENSE
soundmaker-1.0.0.dist-info/METADATA
soundmaker-1.0.0.dist-info/WHEEL
soundmaker-1.0.0.dist-info/top_level.txt
soundmaker-1.0.0.dist-info/RECORD
